pvirie_gcp/__init__.py
pvirie_gcp/artifact_registry.py
pvirie_gcp/cloud_run.py
pvirie_gcp/drive.py
pvirie_gcp/gcp.py
pvirie_gcp/oauth.py
pvirie_gcp/secret_manager.py
pvirie_gcp/sheet.py
pvirie_gcp/storage.py
pvirie_gcp/vertex.py
pvirie_utils-1.6.1.dist-info/licenses/LICENSE
pvirie_utils-1.6.1.dist-info/METADATA
pvirie_utils-1.6.1.dist-info/WHEEL
pvirie_utils-1.6.1.dist-info/top_level.txt
pvirie_utils-1.6.1.dist-info/RECORD
