Metadata-Version: 2.4
Name: pvirie-utils
Version: 1.6.1
Summary: PVirie's python utility functions
Home-page: https://github.com/PVirie/python-utils
Author: Chatavut Viriyasuthee
Author-email: p.virie@gmail.com
Classifier: Programming Language :: Python :: 3
Classifier: License :: OSI Approved :: MIT License
Classifier: Operating System :: OS Independent
Requires-Python: >=3.9
License-File: LICENSE
Requires-Dist: google-api-python-client
Requires-Dist: google-cloud-storage
Requires-Dist: google-cloud-secret-manager
Requires-Dist: pydantic
Dynamic: author
Dynamic: author-email
Dynamic: classifier
Dynamic: description
Dynamic: description-content-type
Dynamic: home-page
Dynamic: license-file
Dynamic: requires-dist
Dynamic: requires-python
Dynamic: summary
